{
    "version" : "1.1.0-M2",
    "project" : {
        "name" : "MacrosJs",
        "directory" : "/CommonSsd/openstrat/target/MacrosJs",
        "sources" : [
            "/CommonSsd/openstrat/target/MacrosJs/src/main/scala-2.12",
            "/CommonSsd/openstrat/target/MacrosJs/src/main/scala",
            "/CommonSsd/openstrat/target/MacrosJs/src/main/java",
            "/CommonSsd/openstrat/MacrosJs/src",
            "/CommonSsd/openstrat/MacrosJs/srcJs",
            "/CommonSsd/openstrat/target/MacrosJs/target/scala-2.12/src_managed/main"
        ],
        "dependencies" : [
        ],
        "classpath" : [
            "/home/rich/.ivy2/cache/org.scala-lang/scala-library/jars/scala-library-2.12.8.jar",
            "/home/rich/.ivy2/cache/org.scala-js/scalajs-library_2.12/jars/scalajs-library_2.12-0.6.26.jar",
            "/home/rich/.ivy2/cache/org.scala-lang/scala-reflect/jars/scala-reflect-2.12.8.jar",
            "/home/rich/.ivy2/cache/org.scala-js/scalajs-dom_sjs0.6_2.12/jars/scalajs-dom_sjs0.6_2.12-0.9.6.jar"
        ],
        "out" : "/CommonSsd/openstrat/.bloop/MacrosJs",
        "classesDir" : "/CommonSsd/openstrat/.bloop/MacrosJs/scala-2.12/classes",
        "resources" : [
            "/CommonSsd/openstrat/target/MacrosJs/src/main/resources",
            "/CommonSsd/openstrat/MacrosJs/res",
            "/CommonSsd/openstrat/target/MacrosJs/target/scala-2.12/resource_managed/main"
        ],
        "scala" : {
            "organization" : "org.scala-lang",
            "name" : "scala-compiler",
            "version" : "2.12.8",
            "options" : [
                "-feature",
                "-language:implicitConversions",
                "-deprecation",
                "-target:jvm-1.8",
                "-encoding",
                "UTF-8",
                "-unchecked",
                "-Xfuture",
                "-Xlint",
                "-P:semanticdb:failures:warning",
                "-P:semanticdb:sourceroot:/CommonSsd/openstrat",
                "-Yrangepos",
                "-Xplugin-require:semanticdb",
                "-Xplugin:/home/rich/.ivy2/cache/org.scala-js/scalajs-compiler_2.12.8/jars/scalajs-compiler_2.12.8-0.6.26.jar",
                "-Xplugin:/home/rich/.ivy2/cache/org.scalameta/semanticdb-scalac_2.12.8/jars/semanticdb-scalac_2.12.8-4.1.0.jar"
            ],
            "jars" : [
                "/home/rich/.ivy2/cache/org.scala-lang/scala-compiler/jars/scala-compiler-2.12.8.jar",
                "/home/rich/.ivy2/cache/org.scala-lang/scala-library/jars/scala-library-2.12.8.jar",
                "/home/rich/.ivy2/cache/org.scala-lang/scala-reflect/jars/scala-reflect-2.12.8.jar",
                "/home/rich/.ivy2/cache/org.scala-lang.modules/scala-xml_2.12/bundles/scala-xml_2.12-1.0.6.jar",
                "/home/rich/.ivy2/cache/jline/jline/jars/jline-2.14.6.jar"
            ],
            "setup" : {
                "order" : "mixed",
                "addLibraryToBootClasspath" : true,
                "addCompilerToClasspath" : false,
                "addExtraJarsToClasspath" : false,
                "manageBootClasspath" : true,
                "filterLibraryFromClasspath" : true
            }
        },
        "java" : {
            "options" : [
            ]
        },
        "test" : {
            "frameworks" : [
                {
                    "names" : [
                        "org.scalacheck.ScalaCheckFramework"
                    ]
                },
                {
                    "names" : [
                        "org.specs2.runner.Specs2Framework",
                        "org.specs2.runner.SpecsFramework"
                    ]
                },
                {
                    "names" : [
                        "org.specs.runner.SpecsFramework"
                    ]
                },
                {
                    "names" : [
                        "org.scalatest.tools.Framework",
                        "org.scalatest.tools.ScalaTestFramework"
                    ]
                },
                {
                    "names" : [
                        "com.novocode.junit.JUnitFramework"
                    ]
                }
            ],
            "options" : {
                "excludes" : [
                ],
                "arguments" : [
                ]
            }
        },
        "platform" : {
            "name" : "js",
            "config" : {
                "version" : "0.6.26",
                "mode" : "debug",
                "kind" : "none",
                "emitSourceMaps" : false,
                "jsdom" : false,
                "toolchain" : [
                ]
            },
            "mainClass" : [
            ]
        },
        "resolution" : {
            "modules" : [
                {
                    "organization" : "org.scala-lang",
                    "name" : "scala-library",
                    "version" : "2.12.8",
                    "artifacts" : [
                        {
                            "name" : "scala-library",
                            "path" : "/home/rich/.ivy2/cache/org.scala-lang/scala-library/jars/scala-library-2.12.8.jar"
                        },
                        {
                            "name" : "scala-library",
                            "classifier" : "sources",
                            "path" : "/home/rich/.ivy2/cache/org.scala-lang/scala-library/srcs/scala-library-2.12.8-sources.jar"
                        }
                    ]
                },
                {
                    "organization" : "org.scala-js",
                    "name" : "scalajs-library_2.12",
                    "version" : "0.6.26",
                    "artifacts" : [
                        {
                            "name" : "scalajs-library_2.12",
                            "path" : "/home/rich/.ivy2/cache/org.scala-js/scalajs-library_2.12/jars/scalajs-library_2.12-0.6.26.jar"
                        },
                        {
                            "name" : "scalajs-library_2.12",
                            "classifier" : "sources",
                            "path" : "/home/rich/.ivy2/cache/org.scala-js/scalajs-library_2.12/srcs/scalajs-library_2.12-0.6.26-sources.jar"
                        }
                    ]
                },
                {
                    "organization" : "org.scala-lang",
                    "name" : "scala-reflect",
                    "version" : "2.12.8",
                    "artifacts" : [
                        {
                            "name" : "scala-reflect",
                            "path" : "/home/rich/.ivy2/cache/org.scala-lang/scala-reflect/jars/scala-reflect-2.12.8.jar"
                        },
                        {
                            "name" : "scala-reflect",
                            "classifier" : "sources",
                            "path" : "/home/rich/.ivy2/cache/org.scala-lang/scala-reflect/srcs/scala-reflect-2.12.8-sources.jar"
                        }
                    ]
                },
                {
                    "organization" : "org.scala-js",
                    "name" : "scalajs-dom_sjs0.6_2.12",
                    "version" : "0.9.6",
                    "artifacts" : [
                        {
                            "name" : "scalajs-dom_sjs0.6_2.12",
                            "path" : "/home/rich/.ivy2/cache/org.scala-js/scalajs-dom_sjs0.6_2.12/jars/scalajs-dom_sjs0.6_2.12-0.9.6.jar"
                        },
                        {
                            "name" : "scalajs-dom_sjs0.6_2.12",
                            "classifier" : "sources",
                            "path" : "/home/rich/.ivy2/cache/org.scala-js/scalajs-dom_sjs0.6_2.12/srcs/scalajs-dom_sjs0.6_2.12-0.9.6-sources.jar"
                        }
                    ]
                }
            ]
        }
    }
}